stryx/__init__.py
stryx/cli.py
stryx/commands.py
stryx/config.py
stryx/lifecycle.py
stryx/py.typed
stryx/run_id.py
stryx/schema.py
stryx/tui.py
stryx/utils.py
stryx-0.1.4.dist-info/WHEEL
stryx-0.1.4.dist-info/entry_points.txt
stryx-0.1.4.dist-info/METADATA
stryx-0.1.4.dist-info/RECORD
