Metadata-Version: 2.3
Name: stryx
Version: 0.1.4
Summary: Typed configuration compiler for ML experiments
Author: Filippos Christianos
Author-email: Filippos Christianos <filippos.christianos@gmail.com>
License: MIT
Classifier: Development Status :: 4 - Beta
Classifier: Intended Audience :: Developers
Classifier: Intended Audience :: Science/Research
Classifier: License :: OSI Approved :: MIT License
Classifier: Programming Language :: Python :: 3
Classifier: Programming Language :: Python :: 3.11
Classifier: Programming Language :: Python :: 3.12
Classifier: Topic :: Software Development :: Libraries :: Python Modules
Classifier: Topic :: Scientific/Engineering :: Artificial Intelligence
Requires-Dist: filelock>=3.0
Requires-Dist: petname>=2.6
Requires-Dist: prompt-toolkit>=3.0.52
Requires-Dist: pydantic>=2
Requires-Dist: pyyaml>=6.0.3
Requires-Dist: rapidfuzz>=3.0.0
Requires-Dist: typer>=0.9.0
Requires-Dist: pytest>=8.0 ; extra == 'dev'
Requires-Dist: torch>=2.0.0 ; extra == 'dev'
Requires-Dist: trl>=0.26.1 ; extra == 'examples'
Requires-Python: >=3.11
Provides-Extra: dev
Provides-Extra: examples
